[{"name":"class BunnyVerseCommand : CommandExecutor","description":"io.github.sobixn.project_vir.command.BunnyVerseCommand","location":"-bunnyverse/io.github.sobixn.project_vir.command/-bunny-verse-command/index.html","searchKeys":["BunnyVerseCommand","class BunnyVerseCommand : CommandExecutor","io.github.sobixn.project_vir.command.BunnyVerseCommand"]},{"name":"class BunnyVerseTabCompleter : TabCompleter","description":"io.github.sobixn.project_vir.command.BunnyVerseTabCompleter","location":"-bunnyverse/io.github.sobixn.project_vir.command/-bunny-verse-tab-completer/index.html","searchKeys":["BunnyVerseTabCompleter","class BunnyVerseTabCompleter : TabCompleter","io.github.sobixn.project_vir.command.BunnyVerseTabCompleter"]},{"name":"class DonationSystem(plugin: JavaPlugin)","description":"io.github.sobixn.project_vir.util.DonationSystem","location":"-bunnyverse/io.github.sobixn.project_vir.util/-donation-system/index.html","searchKeys":["DonationSystem","class DonationSystem(plugin: JavaPlugin)","io.github.sobixn.project_vir.util.DonationSystem"]},{"name":"class Main : JavaPlugin","description":"io.github.sobixn.project_vir.Main","location":"-bunnyverse/io.github.sobixn.project_vir/-main/index.html","searchKeys":["Main","class Main : JavaPlugin","io.github.sobixn.project_vir.Main"]},{"name":"class PlayerJoinMessage : Listener","description":"io.github.sobixn.project_vir.listener.PlayerJoinMessage","location":"-bunnyverse/io.github.sobixn.project_vir.listener/-player-join-message/index.html","searchKeys":["PlayerJoinMessage","class PlayerJoinMessage : Listener","io.github.sobixn.project_vir.listener.PlayerJoinMessage"]},{"name":"class PlayerLeaveMessage : Listener","description":"io.github.sobixn.project_vir.listener.PlayerLeaveMessage","location":"-bunnyverse/io.github.sobixn.project_vir.listener/-player-leave-message/index.html","searchKeys":["PlayerLeaveMessage","class PlayerLeaveMessage : Listener","io.github.sobixn.project_vir.listener.PlayerLeaveMessage"]},{"name":"constructor()","description":"io.github.sobixn.project_vir.Main.Main","location":"-bunnyverse/io.github.sobixn.project_vir/-main/-main.html","searchKeys":["Main","constructor()","io.github.sobixn.project_vir.Main.Main"]},{"name":"constructor()","description":"io.github.sobixn.project_vir.command.BunnyVerseCommand.BunnyVerseCommand","location":"-bunnyverse/io.github.sobixn.project_vir.command/-bunny-verse-command/-bunny-verse-command.html","searchKeys":["BunnyVerseCommand","constructor()","io.github.sobixn.project_vir.command.BunnyVerseCommand.BunnyVerseCommand"]},{"name":"constructor()","description":"io.github.sobixn.project_vir.command.BunnyVerseCommand.RegisterHandler.RegisterHandler","location":"-bunnyverse/io.github.sobixn.project_vir.command/-bunny-verse-command/-register-handler/-register-handler.html","searchKeys":["RegisterHandler","constructor()","io.github.sobixn.project_vir.command.BunnyVerseCommand.RegisterHandler.RegisterHandler"]},{"name":"constructor()","description":"io.github.sobixn.project_vir.command.BunnyVerseCommand.ReloadHandler.ReloadHandler","location":"-bunnyverse/io.github.sobixn.project_vir.command/-bunny-verse-command/-reload-handler/-reload-handler.html","searchKeys":["ReloadHandler","constructor()","io.github.sobixn.project_vir.command.BunnyVerseCommand.ReloadHandler.ReloadHandler"]},{"name":"constructor()","description":"io.github.sobixn.project_vir.command.BunnyVerseCommand.SettingsHandler.SettingsHandler","location":"-bunnyverse/io.github.sobixn.project_vir.command/-bunny-verse-command/-settings-handler/-settings-handler.html","searchKeys":["SettingsHandler","constructor()","io.github.sobixn.project_vir.command.BunnyVerseCommand.SettingsHandler.SettingsHandler"]},{"name":"constructor()","description":"io.github.sobixn.project_vir.command.BunnyVerseTabCompleter.BunnyVerseTabCompleter","location":"-bunnyverse/io.github.sobixn.project_vir.command/-bunny-verse-tab-completer/-bunny-verse-tab-completer.html","searchKeys":["BunnyVerseTabCompleter","constructor()","io.github.sobixn.project_vir.command.BunnyVerseTabCompleter.BunnyVerseTabCompleter"]},{"name":"constructor()","description":"io.github.sobixn.project_vir.command.BunnyVerseTabCompleter.TabCompletionHandler.TabCompletionHandler","location":"-bunnyverse/io.github.sobixn.project_vir.command/-bunny-verse-tab-completer/-tab-completion-handler/-tab-completion-handler.html","searchKeys":["TabCompletionHandler","constructor()","io.github.sobixn.project_vir.command.BunnyVerseTabCompleter.TabCompletionHandler.TabCompletionHandler"]},{"name":"constructor()","description":"io.github.sobixn.project_vir.listener.PlayerJoinMessage.JoinMessageHandler.JoinMessageHandler","location":"-bunnyverse/io.github.sobixn.project_vir.listener/-player-join-message/-join-message-handler/-join-message-handler.html","searchKeys":["JoinMessageHandler","constructor()","io.github.sobixn.project_vir.listener.PlayerJoinMessage.JoinMessageHandler.JoinMessageHandler"]},{"name":"constructor()","description":"io.github.sobixn.project_vir.listener.PlayerJoinMessage.PlayerJoinMessage","location":"-bunnyverse/io.github.sobixn.project_vir.listener/-player-join-message/-player-join-message.html","searchKeys":["PlayerJoinMessage","constructor()","io.github.sobixn.project_vir.listener.PlayerJoinMessage.PlayerJoinMessage"]},{"name":"constructor()","description":"io.github.sobixn.project_vir.listener.PlayerLeaveMessage.LeaveMessageHandler.LeaveMessageHandler","location":"-bunnyverse/io.github.sobixn.project_vir.listener/-player-leave-message/-leave-message-handler/-leave-message-handler.html","searchKeys":["LeaveMessageHandler","constructor()","io.github.sobixn.project_vir.listener.PlayerLeaveMessage.LeaveMessageHandler.LeaveMessageHandler"]},{"name":"constructor()","description":"io.github.sobixn.project_vir.listener.PlayerLeaveMessage.PlayerLeaveMessage","location":"-bunnyverse/io.github.sobixn.project_vir.listener/-player-leave-message/-player-leave-message.html","searchKeys":["PlayerLeaveMessage","constructor()","io.github.sobixn.project_vir.listener.PlayerLeaveMessage.PlayerLeaveMessage"]},{"name":"constructor(file: String = \"bunnyverseData/data.yml\")","description":"io.github.sobixn.project_vir.util.db.PlayerData.PlayerData","location":"-bunnyverse/io.github.sobixn.project_vir.util.db/-player-data/-player-data.html","searchKeys":["PlayerData","constructor(file: String = \"bunnyverseData/data.yml\")","io.github.sobixn.project_vir.util.db.PlayerData.PlayerData"]},{"name":"constructor(plugin: JavaPlugin)","description":"io.github.sobixn.project_vir.util.DonationSystem.DonationSystem","location":"-bunnyverse/io.github.sobixn.project_vir.util/-donation-system/-donation-system.html","searchKeys":["DonationSystem","constructor(plugin: JavaPlugin)","io.github.sobixn.project_vir.util.DonationSystem.DonationSystem"]},{"name":"data class PlayerData(var file: String = \"bunnyverseData/data.yml\")","description":"io.github.sobixn.project_vir.util.db.PlayerData","location":"-bunnyverse/io.github.sobixn.project_vir.util.db/-player-data/index.html","searchKeys":["PlayerData","data class PlayerData(var file: String = \"bunnyverseData/data.yml\")","io.github.sobixn.project_vir.util.db.PlayerData"]},{"name":"fun addData(key: String, value: Any)","description":"io.github.sobixn.project_vir.util.db.DonationConfig.addData","location":"-bunnyverse/io.github.sobixn.project_vir.util.db/-donation-config/add-data.html","searchKeys":["addData","fun addData(key: String, value: Any)","io.github.sobixn.project_vir.util.db.DonationConfig.addData"]},{"name":"fun ensureDonationFilesExist()","description":"io.github.sobixn.project_vir.util.db.DonationConfig.ensureDonationFilesExist","location":"-bunnyverse/io.github.sobixn.project_vir.util.db/-donation-config/ensure-donation-files-exist.html","searchKeys":["ensureDonationFilesExist","fun ensureDonationFilesExist()","io.github.sobixn.project_vir.util.db.DonationConfig.ensureDonationFilesExist"]},{"name":"fun fetchDonations()","description":"io.github.sobixn.project_vir.util.DonationSystem.fetchDonations","location":"-bunnyverse/io.github.sobixn.project_vir.util/-donation-system/fetch-donations.html","searchKeys":["fetchDonations","fun fetchDonations()","io.github.sobixn.project_vir.util.DonationSystem.fetchDonations"]},{"name":"fun getData(key: String): Any?","description":"io.github.sobixn.project_vir.util.db.DonationConfig.getData","location":"-bunnyverse/io.github.sobixn.project_vir.util.db/-donation-config/get-data.html","searchKeys":["getData","fun getData(key: String): Any?","io.github.sobixn.project_vir.util.db.DonationConfig.getData"]},{"name":"fun getPlayerFile(): String","description":"io.github.sobixn.project_vir.util.db.PlayerData.getPlayerFile","location":"-bunnyverse/io.github.sobixn.project_vir.util.db/-player-data/get-player-file.html","searchKeys":["getPlayerFile","fun getPlayerFile(): String","io.github.sobixn.project_vir.util.db.PlayerData.getPlayerFile"]},{"name":"fun isChzzkStreamerRegistered(id: String): Boolean","description":"io.github.sobixn.project_vir.util.db.DonationConfig.isChzzkStreamerRegistered","location":"-bunnyverse/io.github.sobixn.project_vir.util.db/-donation-config/is-chzzk-streamer-registered.html","searchKeys":["isChzzkStreamerRegistered","fun isChzzkStreamerRegistered(id: String): Boolean","io.github.sobixn.project_vir.util.db.DonationConfig.isChzzkStreamerRegistered"]},{"name":"fun isSoopUserRegistered(id: String): Boolean","description":"io.github.sobixn.project_vir.util.db.DonationConfig.isSoopUserRegistered","location":"-bunnyverse/io.github.sobixn.project_vir.util.db/-donation-config/is-soop-user-registered.html","searchKeys":["isSoopUserRegistered","fun isSoopUserRegistered(id: String): Boolean","io.github.sobixn.project_vir.util.db.DonationConfig.isSoopUserRegistered"]},{"name":"fun loadData()","description":"io.github.sobixn.project_vir.util.db.DonationConfig.loadData","location":"-bunnyverse/io.github.sobixn.project_vir.util.db/-donation-config/load-data.html","searchKeys":["loadData","fun loadData()","io.github.sobixn.project_vir.util.db.DonationConfig.loadData"]},{"name":"fun onJoin(e: PlayerJoinEvent)","description":"io.github.sobixn.project_vir.listener.PlayerJoinMessage.onJoin","location":"-bunnyverse/io.github.sobixn.project_vir.listener/-player-join-message/on-join.html","searchKeys":["onJoin","fun onJoin(e: PlayerJoinEvent)","io.github.sobixn.project_vir.listener.PlayerJoinMessage.onJoin"]},{"name":"fun onPlayerLeave(e: PlayerQuitEvent)","description":"io.github.sobixn.project_vir.listener.PlayerLeaveMessage.onPlayerLeave","location":"-bunnyverse/io.github.sobixn.project_vir.listener/-player-leave-message/on-player-leave.html","searchKeys":["onPlayerLeave","fun onPlayerLeave(e: PlayerQuitEvent)","io.github.sobixn.project_vir.listener.PlayerLeaveMessage.onPlayerLeave"]},{"name":"fun registerChzzkStreamer(playerName: String, id: String)","description":"io.github.sobixn.project_vir.util.db.DonationConfig.registerChzzkStreamer","location":"-bunnyverse/io.github.sobixn.project_vir.util.db/-donation-config/register-chzzk-streamer.html","searchKeys":["registerChzzkStreamer","fun registerChzzkStreamer(playerName: String, id: String)","io.github.sobixn.project_vir.util.db.DonationConfig.registerChzzkStreamer"]},{"name":"fun registerSoopUser(playerName: String, id: String)","description":"io.github.sobixn.project_vir.util.db.DonationConfig.registerSoopUser","location":"-bunnyverse/io.github.sobixn.project_vir.util.db/-donation-config/register-soop-user.html","searchKeys":["registerSoopUser","fun registerSoopUser(playerName: String, id: String)","io.github.sobixn.project_vir.util.db.DonationConfig.registerSoopUser"]},{"name":"fun saveData()","description":"io.github.sobixn.project_vir.util.db.DonationConfig.saveData","location":"-bunnyverse/io.github.sobixn.project_vir.util.db/-donation-config/save-data.html","searchKeys":["saveData","fun saveData()","io.github.sobixn.project_vir.util.db.DonationConfig.saveData"]},{"name":"fun saveInfoData()","description":"io.github.sobixn.project_vir.util.db.DonationConfig.saveInfoData","location":"-bunnyverse/io.github.sobixn.project_vir.util.db/-donation-config/save-info-data.html","searchKeys":["saveInfoData","fun saveInfoData()","io.github.sobixn.project_vir.util.db.DonationConfig.saveInfoData"]},{"name":"fun setPlayerFile(newFile: String)","description":"io.github.sobixn.project_vir.util.db.PlayerData.setPlayerFile","location":"-bunnyverse/io.github.sobixn.project_vir.util.db/-player-data/set-player-file.html","searchKeys":["setPlayerFile","fun setPlayerFile(newFile: String)","io.github.sobixn.project_vir.util.db.PlayerData.setPlayerFile"]},{"name":"fun setPlugin(plugin: JavaPlugin)","description":"io.github.sobixn.project_vir.util.db.DonationConfig.setPlugin","location":"-bunnyverse/io.github.sobixn.project_vir.util.db/-donation-config/set-plugin.html","searchKeys":["setPlugin","fun setPlugin(plugin: JavaPlugin)","io.github.sobixn.project_vir.util.db.DonationConfig.setPlugin"]},{"name":"fun start()","description":"io.github.sobixn.project_vir.util.DonationSystem.start","location":"-bunnyverse/io.github.sobixn.project_vir.util/-donation-system/start.html","searchKeys":["start","fun start()","io.github.sobixn.project_vir.util.DonationSystem.start"]},{"name":"lateinit var instance: Main","description":"io.github.sobixn.project_vir.Main.Companion.instance","location":"-bunnyverse/io.github.sobixn.project_vir/-main/-companion/instance.html","searchKeys":["instance","lateinit var instance: Main","io.github.sobixn.project_vir.Main.Companion.instance"]},{"name":"object Companion","description":"io.github.sobixn.project_vir.Main.Companion","location":"-bunnyverse/io.github.sobixn.project_vir/-main/-companion/index.html","searchKeys":["Companion","object Companion","io.github.sobixn.project_vir.Main.Companion"]},{"name":"object DonationConfig","description":"io.github.sobixn.project_vir.util.db.DonationConfig","location":"-bunnyverse/io.github.sobixn.project_vir.util.db/-donation-config/index.html","searchKeys":["DonationConfig","object DonationConfig","io.github.sobixn.project_vir.util.db.DonationConfig"]},{"name":"open class JoinMessageHandler","description":"io.github.sobixn.project_vir.listener.PlayerJoinMessage.JoinMessageHandler","location":"-bunnyverse/io.github.sobixn.project_vir.listener/-player-join-message/-join-message-handler/index.html","searchKeys":["JoinMessageHandler","open class JoinMessageHandler","io.github.sobixn.project_vir.listener.PlayerJoinMessage.JoinMessageHandler"]},{"name":"open class LeaveMessageHandler","description":"io.github.sobixn.project_vir.listener.PlayerLeaveMessage.LeaveMessageHandler","location":"-bunnyverse/io.github.sobixn.project_vir.listener/-player-leave-message/-leave-message-handler/index.html","searchKeys":["LeaveMessageHandler","open class LeaveMessageHandler","io.github.sobixn.project_vir.listener.PlayerLeaveMessage.LeaveMessageHandler"]},{"name":"open class RegisterHandler","description":"io.github.sobixn.project_vir.command.BunnyVerseCommand.RegisterHandler","location":"-bunnyverse/io.github.sobixn.project_vir.command/-bunny-verse-command/-register-handler/index.html","searchKeys":["RegisterHandler","open class RegisterHandler","io.github.sobixn.project_vir.command.BunnyVerseCommand.RegisterHandler"]},{"name":"open class ReloadHandler","description":"io.github.sobixn.project_vir.command.BunnyVerseCommand.ReloadHandler","location":"-bunnyverse/io.github.sobixn.project_vir.command/-bunny-verse-command/-reload-handler/index.html","searchKeys":["ReloadHandler","open class ReloadHandler","io.github.sobixn.project_vir.command.BunnyVerseCommand.ReloadHandler"]},{"name":"open class SettingsHandler","description":"io.github.sobixn.project_vir.command.BunnyVerseCommand.SettingsHandler","location":"-bunnyverse/io.github.sobixn.project_vir.command/-bunny-verse-command/-settings-handler/index.html","searchKeys":["SettingsHandler","open class SettingsHandler","io.github.sobixn.project_vir.command.BunnyVerseCommand.SettingsHandler"]},{"name":"open class TabCompletionHandler","description":"io.github.sobixn.project_vir.command.BunnyVerseTabCompleter.TabCompletionHandler","location":"-bunnyverse/io.github.sobixn.project_vir.command/-bunny-verse-tab-completer/-tab-completion-handler/index.html","searchKeys":["TabCompletionHandler","open class TabCompletionHandler","io.github.sobixn.project_vir.command.BunnyVerseTabCompleter.TabCompletionHandler"]},{"name":"open fun broadcastLeaveMessage()","description":"io.github.sobixn.project_vir.listener.PlayerLeaveMessage.LeaveMessageHandler.broadcastLeaveMessage","location":"-bunnyverse/io.github.sobixn.project_vir.listener/-player-leave-message/-leave-message-handler/broadcast-leave-message.html","searchKeys":["broadcastLeaveMessage","open fun broadcastLeaveMessage()","io.github.sobixn.project_vir.listener.PlayerLeaveMessage.LeaveMessageHandler.broadcastLeaveMessage"]},{"name":"open fun complete(): List<String>?","description":"io.github.sobixn.project_vir.command.BunnyVerseTabCompleter.TabCompletionHandler.complete","location":"-bunnyverse/io.github.sobixn.project_vir.command/-bunny-verse-tab-completer/-tab-completion-handler/complete.html","searchKeys":["complete","open fun complete(): List<String>?","io.github.sobixn.project_vir.command.BunnyVerseTabCompleter.TabCompletionHandler.complete"]},{"name":"open fun register()","description":"io.github.sobixn.project_vir.command.BunnyVerseCommand.RegisterHandler.register","location":"-bunnyverse/io.github.sobixn.project_vir.command/-bunny-verse-command/-register-handler/register.html","searchKeys":["register","open fun register()","io.github.sobixn.project_vir.command.BunnyVerseCommand.RegisterHandler.register"]},{"name":"open fun reload()","description":"io.github.sobixn.project_vir.command.BunnyVerseCommand.ReloadHandler.reload","location":"-bunnyverse/io.github.sobixn.project_vir.command/-bunny-verse-command/-reload-handler/reload.html","searchKeys":["reload","open fun reload()","io.github.sobixn.project_vir.command.BunnyVerseCommand.ReloadHandler.reload"]},{"name":"open fun setJoinMessage(): String","description":"io.github.sobixn.project_vir.listener.PlayerJoinMessage.JoinMessageHandler.setJoinMessage","location":"-bunnyverse/io.github.sobixn.project_vir.listener/-player-join-message/-join-message-handler/set-join-message.html","searchKeys":["setJoinMessage","open fun setJoinMessage(): String","io.github.sobixn.project_vir.listener.PlayerJoinMessage.JoinMessageHandler.setJoinMessage"]},{"name":"open fun settings()","description":"io.github.sobixn.project_vir.command.BunnyVerseCommand.SettingsHandler.settings","location":"-bunnyverse/io.github.sobixn.project_vir.command/-bunny-verse-command/-settings-handler/settings.html","searchKeys":["settings","open fun settings()","io.github.sobixn.project_vir.command.BunnyVerseCommand.SettingsHandler.settings"]},{"name":"open override fun getLogger(): Logger","description":"io.github.sobixn.project_vir.Main.getLogger","location":"-bunnyverse/io.github.sobixn.project_vir/-main/get-logger.html","searchKeys":["getLogger","open override fun getLogger(): Logger","io.github.sobixn.project_vir.Main.getLogger"]},{"name":"open override fun onCommand(sender: CommandSender, command: Command, label: String, args: Array<out String>): Boolean","description":"io.github.sobixn.project_vir.command.BunnyVerseCommand.onCommand","location":"-bunnyverse/io.github.sobixn.project_vir.command/-bunny-verse-command/on-command.html","searchKeys":["onCommand","open override fun onCommand(sender: CommandSender, command: Command, label: String, args: Array<out String>): Boolean","io.github.sobixn.project_vir.command.BunnyVerseCommand.onCommand"]},{"name":"open override fun onDisable()","description":"io.github.sobixn.project_vir.Main.onDisable","location":"-bunnyverse/io.github.sobixn.project_vir/-main/on-disable.html","searchKeys":["onDisable","open override fun onDisable()","io.github.sobixn.project_vir.Main.onDisable"]},{"name":"open override fun onEnable()","description":"io.github.sobixn.project_vir.Main.onEnable","location":"-bunnyverse/io.github.sobixn.project_vir/-main/on-enable.html","searchKeys":["onEnable","open override fun onEnable()","io.github.sobixn.project_vir.Main.onEnable"]},{"name":"open override fun onTabComplete(sender: CommandSender, command: Command, alias: String, args: Array<out String>): List<String>?","description":"io.github.sobixn.project_vir.command.BunnyVerseTabCompleter.onTabComplete","location":"-bunnyverse/io.github.sobixn.project_vir.command/-bunny-verse-tab-completer/on-tab-complete.html","searchKeys":["onTabComplete","open override fun onTabComplete(sender: CommandSender, command: Command, alias: String, args: Array<out String>): List<String>?","io.github.sobixn.project_vir.command.BunnyVerseTabCompleter.onTabComplete"]},{"name":"val logger: Logger","description":"io.github.sobixn.project_vir.Main.Companion.logger","location":"-bunnyverse/io.github.sobixn.project_vir/-main/-companion/logger.html","searchKeys":["logger","val logger: Logger","io.github.sobixn.project_vir.Main.Companion.logger"]},{"name":"var file: String","description":"io.github.sobixn.project_vir.util.db.PlayerData.file","location":"-bunnyverse/io.github.sobixn.project_vir.util.db/-player-data/file.html","searchKeys":["file","var file: String","io.github.sobixn.project_vir.util.db.PlayerData.file"]}]
